AUTHORS.rst
CONTRIBUTING.rst
HISTORY.rst
LICENSE
MANIFEST.in
README.rst
setup.cfg
setup.py
docs/Makefile
docs/authors.rst
docs/conf.py
docs/contributing.rst
docs/history.rst
docs/index.rst
docs/installation.rst
docs/jobrunner.rst
docs/make.bat
docs/modules.rst
docs/readme.rst
docs/usage.rst
jobrunner/__init__.py
jobrunner/jobrunner.py
jobrunner.egg-info/PKG-INFO
jobrunner.egg-info/SOURCES.txt
jobrunner.egg-info/dependency_links.txt
jobrunner.egg-info/not-zip-safe
jobrunner.egg-info/requires.txt
jobrunner.egg-info/top_level.txt
tests/__init__.py
tests/test_jobrunner.py