Metadata-Version: 1.1
Name: jobrunner
Version: 1.1.0
Summary: An abstraction layer to run jobs on HPC clusters using Grid Engine, Torque, or locally.
Home-page: https://github.com/CFSAN-Biostatistics/jobrunner
Author: Steve Davis
Author-email: steven.davis@fda.hhs.gov
License: BSD
Keywords: bioinformatics,NGS,jobrunner
Platform: UNKNOWN
Classifier: Development Status :: 5 - Production/Stable
Classifier: Intended Audience :: Developers
Classifier: License :: OSI Approved :: BSD License
Classifier: Natural Language :: English
Classifier: Programming Language :: Python :: 2
Classifier: Programming Language :: Python :: 2.7
Classifier: Programming Language :: Python :: 3
Classifier: Programming Language :: Python :: 3.4
Classifier: Programming Language :: Python :: 3.5
Classifier: Programming Language :: Python :: 3.6
